xacrodoc/__init__.py
xacrodoc/cli.py
xacrodoc/packages.py
xacrodoc/version.py
xacrodoc/xacrodoc.py
xacrodoc/xacro/.bazelignore
xacrodoc/xacro/.bazelversion
xacrodoc/xacro/.git
xacrodoc/xacro/.gitignore
xacrodoc/xacro/.pre-commit-config.yaml
xacrodoc/xacro/BUILD.bazel
xacrodoc/xacro/CHANGELOG.rst
xacrodoc/xacro/CMakeLists.txt
xacrodoc/xacro/LICENSE
xacrodoc/xacro/MODULE.bazel
xacrodoc/xacro/README.md
xacrodoc/xacro/colcon.pkg
xacrodoc/xacro/package.xml
xacrodoc/xacro/pyproject.toml
xacrodoc/xacro/setup.cfg
xacrodoc/xacro/.github/FUNDING.yml
xacrodoc/xacro/.github/workflows/bazel.yml
xacrodoc/xacro/.github/workflows/ci.yaml
xacrodoc/xacro/.github/workflows/format.yaml
xacrodoc/xacro/.github/workflows/pypi.yaml
xacrodoc/xacro/bazel/BUILD.bazel
xacrodoc/xacro/bazel/README.md
xacrodoc/xacro/bazel/defs.bzl
xacrodoc/xacro/bazel/requirements.in
xacrodoc/xacro/bazel/requirements_lock.txt
xacrodoc/xacro/bazel/integration_test/.bazelversion
xacrodoc/xacro/bazel/integration_test/BUILD.bazel
xacrodoc/xacro/bazel/integration_test/MODULE.bazel
xacrodoc/xacro/bazel/integration_test/expected/conditional_default.xml
xacrodoc/xacro/bazel/integration_test/expected/conditional_false.xml
xacrodoc/xacro/bazel/integration_test/expected/my_complex_model.xml
xacrodoc/xacro/bazel/integration_test/expected/sample1.xml
xacrodoc/xacro/bazel/integration_test/expected/sample2.xml
xacrodoc/xacro/bazel/integration_test/inputs/box.xml
xacrodoc/xacro/bazel/integration_test/inputs/complex.xml.xacro
xacrodoc/xacro/bazel/integration_test/inputs/conditional.xml.xacro
xacrodoc/xacro/bazel/integration_test/inputs/sample1.xml.xacro
xacrodoc/xacro/bazel/integration_test/inputs/sample2.xml.xacro
xacrodoc/xacro/bazel/integration_test/inputs/deeply/nested/dependency.xml.xacro
xacrodoc/xacro/cmake/xacro-extras.cmake
xacrodoc/xacro/scripts/completion.bash
xacrodoc/xacro/test/A.xacro
xacrodoc/xacro/test/B.xacro
xacrodoc/xacro/test/CMakeLists.txt
xacrodoc/xacro/test/broken.xacro
xacrodoc-1.3.1.dist-info/METADATA
xacrodoc-1.3.1.dist-info/WHEEL
xacrodoc-1.3.1.dist-info/entry_points.txt
xacrodoc-1.3.1.dist-info/licenses/LICENSE
xacrodoc-1.3.1.dist-info/RECORD
