Metadata-Version: 2.4
Name: xacrodoc
Version: 1.3.1
Summary: Compile xacro files to URDF or MJCF from Python or the command line (no ROS required).
Author-email: Adam Heins <mail@adamheins.com>
License: MIT
License-File: LICENSE
Requires-Python: >=3.8
Requires-Dist: docutils!=0.21
Requires-Dist: pyyaml>=6.0
Requires-Dist: rospkg>=1.5.0
Provides-Extra: mujoco
Requires-Dist: mujoco>=3.2.3; extra == 'mujoco'
